Workbook
Name NativeTimeline_Order_Date: #N/A
Name Slicer_Category: #N/A
Name Slicer_Region_Zone: #N/A

Sheet Dim_Products
A1: Product_ID | B1: Category | C1: Sub_Category | D1: Unit_Cost | E1: Unit_Price
A2: PROD-101 | B2: Electronics | C2: Audio & Sound | D2: 120 | E2: 250
A3: PROD-102 | B3: Electronics | C3: Mobile Accessories | D3: 15 | E3: 45
A4: PROD-103 | B4: Office Supply | C4: Ergonomic Chairs | D4: 85 | E4: 180
A5: PROD-104 | B5: Office Supply | C5: Storage & Organization | D5: 12 | E5: 30
A6: PROD-105 | B6: Home & Kitchen | C6: Smart Lighting | D6: 25 | E6: 65

Sheet Dim_Customers
A1: Customer_ID | B1: Customer_Name | C1: Region_Zone | D1: State | E1: Postal_Code
A2: CUST-501 | B2: Acme Logistics | C2: North America - East | D2: NY | E2: 10001
A3: CUST-502 | B3: Nexus Global | C3: North America - West | D3: CA | E3: 90210
A4: CUST-503 | B4: Horizon Retail | C4: North America - South | D4: TX | E4: 75001
A5: CUST-504 | B5: Stellar Media | C5: Europe - Central | D5: DE | E5: 10115
A6: CUST-505 | B6: Pacific Rim Trading | C6: Asia - Pacific | D6: SG | E6: 18989

Sheet Fact_Sales
A1: Order_ID | B1: Order_Date | C1: Customer_ID | D1: Product_ID | E1: Quantity | F1: Discount_Pct | G1: Category | H1: Unit_Price | I1: Unit_Cost | J1: Gross_Revenue | K1: Net_Revenue | L1: Total_Profit | M1: Region_Zone
A2: ORD-9001 | B2: 46249 | C2: CUST-501 | D2: PROD-101 | E2: 4 | F2: 0.05 | G2: =_xlfn.XLOOKUP(D2, Dim_Products!A:A, Dim_Products!B:B, "Unknown") -> Electronics | H2: =_xlfn.XLOOKUP(D2, Dim_Products!A:A, Dim_Products!E:E, 0) -> 250 | I2: =_xlfn.XLOOKUP(D2, Dim_Products!A:A, Dim_Products!D:D, 0) -> 120 | J2: =E2 * H2 -> 1000 | K2: =J2 * (1 - F2) -> 950 | L2: =K2 - (E2 * I2) -> 470 | M2: =_xlfn.XLOOKUP(C2, Dim_Customers!A:A, Dim_Customers!C:C, "Unknown") -> North America - East
A3: ORD-9002 | B3: 46252 | C3: CUST-502 | D3: PROD-102 | E3: 15 | F3: 0 | G3: =_xlfn.XLOOKUP(D3, Dim_Products!A:A, Dim_Products!B:B, "Unknown") -> Electronics | H3: =_xlfn.XLOOKUP(D3, Dim_Products!A:A, Dim_Products!E:E, 0) -> 45 | I3: =_xlfn.XLOOKUP(D3, Dim_Products!A:A, Dim_Products!D:D, 0) -> 15 | J3: =E3 * H3 -> 675 | K3: =J3 * (1 - F3) -> 675 | L3: =K3 - (E3 * I3) -> 450 | M3: =_xlfn.XLOOKUP(C3, Dim_Customers!A:A, Dim_Customers!C:C, "Unknown") -> North America - West
A4: ORD-9003 | B4: 46267 | C4: CUST-503 | D4: PROD-103 | E4: 8 | F4: 0.1 | G4: =_xlfn.XLOOKUP(D4, Dim_Products!A:A, Dim_Products!B:B, "Unknown") -> Office Supply | H4: =_xlfn.XLOOKUP(D4, Dim_Products!A:A, Dim_Products!E:E, 0) -> 180 | I4: =_xlfn.XLOOKUP(D4, Dim_Products!A:A, Dim_Products!D:D, 0) -> 85 | J4: =E4 * H4 -> 1440 | K4: =J4 * (1 - F4) -> 1296 | L4: =K4 - (E4 * I4) -> 616 | M4: =_xlfn.XLOOKUP(C4, Dim_Customers!A:A, Dim_Customers!C:C, "Unknown") -> North America - South
A5: ORD-9004 | B5: 46279 | C5: CUST-504 | D5: PROD-104 | E5: 25 | F5: 0 | G5: =_xlfn.XLOOKUP(D5, Dim_Products!A:A, Dim_Products!B:B, "Unknown") -> Office Supply | H5: =_xlfn.XLOOKUP(D5, Dim_Products!A:A, Dim_Products!E:E, 0) -> 30 | I5: =_xlfn.XLOOKUP(D5, Dim_Products!A:A, Dim_Products!D:D, 0) -> 12 | J5: =E5 * H5 -> 750 | K5: =J5 * (1 - F5) -> 750 | L5: =K5 - (E5 * I5) -> 450 | M5: =_xlfn.XLOOKUP(C5, Dim_Customers!A:A, Dim_Customers!C:C, "Unknown") -> Europe - Central
A6: ORD-9005 | B6: 46293 | C6: CUST-505 | D6: PROD-105 | E6: 12 | F6: 0.05 | G6: =_xlfn.XLOOKUP(D6, Dim_Products!A:A, Dim_Products!B:B, "Unknown") -> Home & Kitchen | H6: =_xlfn.XLOOKUP(D6, Dim_Products!A:A, Dim_Products!E:E, 0) -> 65 | I6: =_xlfn.XLOOKUP(D6, Dim_Products!A:A, Dim_Products!D:D, 0) -> 25 | J6: =E6 * H6 -> 780 | K6: =J6 * (1 - F6) -> 741 | L6: =K6 - (E6 * I6) -> 441 | M6: =_xlfn.XLOOKUP(C6, Dim_Customers!A:A, Dim_Customers!C:C, "Unknown") -> Asia - Pacific

Sheet Executive_Dashboard
B1: TOTAL NET REVENUE | E1: TOTAL NET PROFIT | H1: AVERAGE ORDER VALUE | K1: TOTAL UNITS SOLD
B2: =SUM(Fact_Sales!K2:K6) -> 4412 | E2: =SUM(Fact_Sales!L2:L6) -> 2427 | H2: =AVERAGE(Fact_Sales!K2:K6) -> 882.4 | K2: =SUM(Fact_Sales!E2:E6) -> 64

Sheet Pivot_Data
A1: Row Labels | B1: Sum of Net_Revenue | E1: Row Labels | F1: Sum of Net_Revenue | G1: Sum of Total_Profit | I1: Row Labels | J1: Sum of Net_Revenue
A2: Electronics | B2: 1625 | E2: Asia - Pacific | F2: 741 | G2: 441 | I2: Aug | J2: 1625
A3: Home & Kitchen | B3: 741 | E3: Europe - Central | F3: 750 | G3: 450 | I3: Sep | J3: 2787
A4: Office Supply | B4: 2046 | E4: North America - East | F4: 950 | G4: 470 | I4: Grand Total | J4: 4412
A5: Grand Total | B5: 4412 | E5: North America - South | F5: 1296 | G5: 616
E6: North America - West | F6: 675 | G6: 450
E7: Grand Total | F7: 4412 | G7: 2427
